{"is_source_file": true, "format": "JavaScript (React JSX)", "description": "A React component named PromoBar that displays an announcement message based on site content context, likely used for promotional messages.", "external_files": ["../providers/ContentContext"], "external_methods": ["useContent"], "published": [], "classes": [], "methods": [{"name": "PromoBar()", "description": "React functional component that renders a promotional announcement bar if enabled in the site content.", "scope": "", "scopeKind": ""}], "calls": ["useContent"], "search-terms": ["PromoBar", "announcement", "ContentContext", "useContent", "site", "message", "threshold", "code"], "state": 2, "file_id": 67, "knowledge_revision": 197, "git_revision": "8bb5342c099a0f849be6689be11f11b6b0920bf3", "ctags": [{"_type": "tag", "name": "PromoBar", "path": "/home/kavia/workspace/code-generation/noorvaan-candle-e-commerce-platform-72426-72482/noorvaan_web_frontend/src/components/PromoBar.js", "pattern": "/^export default function PromoBar() {$/", "language": "JavaScript", "kind": "function", "signature": "()"}], "hash": "da2ccf4eae736146d5d8f7d4ff8ef08f", "format-version": 4, "code-base-name": "NoorvaanWebFrontend", "filename": "noorvaan_web_frontend/src/components/PromoBar.js", "revision_history": [{"197": "8bb5342c099a0f849be6689be11f11b6b0920bf3"}]}